advselenium/__init__.py
advselenium/browser.py
advselenium/cli.py
advselenium/elements.py
advselenium/exceptions.py
advselenium/pom.py
advselenium/py.typed
advselenium/utils.py
advselenium/waits.py
advselenium-0.1.1.dist-info/licenses/LICENSE
advselenium-0.1.1.dist-info/METADATA
advselenium-0.1.1.dist-info/WHEEL
advselenium-0.1.1.dist-info/entry_points.txt
advselenium-0.1.1.dist-info/top_level.txt
advselenium-0.1.1.dist-info/RECORD
