Metadata-Version: 2.4
Name: advselenium
Version: 0.1.1
Summary: Advanced Selenium toolkit: smart waits, resilient actions, stealth, POM base, and handy CLI.
Author-email: Amal Alexander <amalalex95@gmail.com>
Maintainer-email: Amal Alexander <amalalex95@gmail.com>
License: MIT License
Project-URL: LinkedIn, https://www.linkedin.com/in/amal-alexander-305780131/
Keywords: selenium,automation,testing,web scraping,e2e,browser
Classifier: Programming Language :: Python :: 3
Classifier: Programming Language :: Python :: 3 :: Only
Classifier: License :: OSI Approved :: MIT License
Classifier: Operating System :: OS Independent
Classifier: Topic :: Software Development :: Testing
Classifier: Typing :: Typed
Requires-Python: >=3.9
License-File: LICENSE
Requires-Dist: selenium>=4.22.0
Requires-Dist: webdriver-manager>=4.0.1
Requires-Dist: tenacity>=8.2.3
Requires-Dist: typing-extensions>=4.9.0
Dynamic: license-file
